{
  "id": "research/game-theory/ostrom-games-cpr",
  "title": "Governance systems",
  "description": "Game Theory refers to the mathematical study of decision-making, of conflict and strategy in social situations. It helps explain how we interact in key decision-making processes.",
  "source": "@site/docs/research/game-theory/ostrom-games-cpr.md",
  "sourceDirName": "research/game-theory",
  "slug": "/research/game-theory/ostrom-games-cpr",
  "permalink": "/docs/research/game-theory/ostrom-games-cpr",
  "draft": false,
  "unlisted": false,
  "tags": [],
  "version": "current",
  "frontMatter": {
    "title": "Governance systems",
    "sidebar-position": 1
  },
  "sidebar": "researchSidebar",
  "next": {
    "title": "The Prisoners dilemma",
    "permalink": "/docs/research/game-theory/prisoners-dilemma"
  }
}